bouse_mcp_time/__init__.py
bouse_mcp_time/__main__.py
bouse_mcp_time/mcp_time.py
bouse_mcp_time/time_tools.py
bouse_mcp_time-0.1.0.dist-info/METADATA
bouse_mcp_time-0.1.0.dist-info/WHEEL
bouse_mcp_time-0.1.0.dist-info/entry_points.txt
bouse_mcp_time-0.1.0.dist-info/licenses/LICENSE
bouse_mcp_time-0.1.0.dist-info/RECORD
