Metadata-Version: 2.4
Name: bouse-mcp-time
Version: 0.1.0
Summary: An MCP service providing time information and time calculations
Author: bouse
License: MIT License
License-File: LICENSE
Keywords: agent,ai,llm,mcp,time,timezone
Classifier: Programming Language :: Python :: 3
Requires-Python: >=3.10
Requires-Dist: fastmcp>=2.8.1
Requires-Dist: pytz
